Workbook

Sheet README
A1: THE INFORMATION WAR — Phase 1 scenario workbook (ORGANISER ONLY)
A3: Generated from app/src/scenario/scenario.json by tools/build_phase1.py. The JSON file is the source the server loads;
A4: if you change numbers here, copy them back into scenario.json (or edit the JSON and regenerate).
A6: Legend: blue text = input you may edit · black = formula · green = formula pulling from another sheet.
A7: Percent inputs are stored as fractions (0.05 = 5%).
A9: Sheets: Parameters · Stocks · Hidden State · Public News · Private Signals · Allocation · Balance Check · Research · Forecasts
A10: Intel groups: team 1 → A, team 2 → B, … team 7 → A again (round-robin by team number).

Sheet Parameters
A1: Parameter | B1: Value | C1: Notes
A2: Starting capital | B2: 100000 | C2: Total value each team starts with (cash + share endowment).
A3: Starting cash | B3: 60000 | C3: Nominal cash component. Actual cash = capital − endowment value, so every team starts at exactly the starting capital.
A4: Endowment per stock | B4: 4000 | C4: Credits of each stock given at start (shares = value / start price, rounded).
A5: Max position value per stock | B5: 30000 | C5: Share cap = INT(this / start price). Fixed for the event.
A6: Max order notional | B6: 12000 | C6: Quantity × price per order.
A7: Max open orders per team | B7: 25
A8: Market order collar | B8: 0.03 | C8: Market orders fill only within this % of the best opposite price at submission.
A9: Research credits per team | B9: 3 | C9: For the whole event; separate from cash.
A10: Rounds | B10: 10
A11: News phase (s) | B11: 20
A12: Trading phase (s) | B12: 200
A13: Settlement phase (s) | B13: 20
A14: RV weight on VWAP gap | B14: 0.3 | C14: RV = F + weight × clamp(VWAP − F, ±cap × F).
A15: RV cap | B15: 0.06
A16: RV min volume (shares) | B16: 150 | C16: VWAP ignored below this round volume.
A17: RV min trades | B17: 5
A18: RV min distinct teams | B18: 3
A19: MM half-spread | B19: 0.01 | C19: Market-maker best bid/ask distance from its mid.
A20: MM level step | B20: 0.01
A21: MM levels per side | B21: 3
A22: MM level notional | B22: 6000
A23: MM skew per 10k net flow | B23: 0.01 | C23: Mid shifts this much per 10,000 credits teams net-buy from the MM.
A24: MM max skew | B24: 0.08

Sheet Stocks
A1: Ticker | B1: Company | C1: Sector | D1: Description | E1: Start price | F1: Volatility | G1: Known links | H1: Starting shares | I1: Max shares | J1: Start holding value
A2: NVTX | B2: Novatex Devices | C2: Consumer technology | D2: Smartphones, wearables and home devices. Relies on imported components; launches a flagship handset this season. | E2: 142 | F2: Very high | G2: Buys components from Forgeline. Sensitive to interest rates (growth stock). | H2: =ROUND(Parameters!$B$4/E2,0) -> 28 | I2: =INT(Parameters!$B$5/E2) -> 211 | J2: =H2*E2 -> 3976
A3: HBFG | B3: Harbourline Financial Group | C3: Banking and financial services | D3: Valdoria's third-largest bank: retail deposits, business lending and a trading desk. | E3: 88 | F3: High | G3: Earns more when interest rates rise. Lends to Solaris Ridge and Tidewell. | H3: =ROUND(Parameters!$B$4/E3,0) -> 45 | I3: =INT(Parameters!$B$5/E3) -> 340 | J3: =H3*E3 -> 3960
A4: PTRL | B4: Petralis Energy | C4: Energy | D4: Oil and gas producer with offshore fields and a fuel distribution arm. | E4: 74 | F4: High | G4: Competes with renewables for energy policy. Exports priced in foreign currency. | H4: =ROUND(Parameters!$B$4/E4,0) -> 54 | I4: =INT(Parameters!$B$5/E4) -> 405 | J4: =H4*E4 -> 3996
A5: CLVH | B5: Calvera Health | C5: Healthcare | D5: Pharmaceutical developer. Its lead drug VX-7 (arthritis) is in late-stage trials. | E5: 126 | F5: Very high | G5: Value depends heavily on VX-7 regulatory outcome and competitors. | H5: =ROUND(Parameters!$B$4/E5,0) -> 32 | I5: =INT(Parameters!$B$5/E5) -> 238 | J5: =H5*E5 -> 4032
A6: MRLW | B6: Marlowe & Kent | C6: Retail and consumer goods | D6: Department stores and online retail. Holiday season is half of annual profit. | E6: 64 | F6: High | G6: Imports most holiday stock through the Port of Ashmouth. Sensitive to consumer spending. | H6: =ROUND(Parameters!$B$4/E6,0) -> 63 | I6: =INT(Parameters!$B$5/E6) -> 468 | J6: =H6*E6 -> 4032
A7: FRGE | B7: Forgeline Industries | C7: Industrial manufacturing | D7: Precision components: electronics parts, gearboxes and industrial bearings. | E7: 96 | F7: High | G7: Supplies Novatex and the wind-turbine industry. Depends on imported bearings. | H7: =ROUND(Parameters!$B$4/E7,0) -> 42 | I7: =INT(Parameters!$B$5/E7) -> 312 | J7: =H7*E7 -> 4032
A8: TDWL | B8: Tidewell Logistics | C8: Logistics and shipping | D8: Container terminals, trucking and Valdoria's only inland rail-freight corridor. | E8: 68 | F8: High | G8: Fuel is a major cost. Moves goods for Marlowe & Kent and Greenfield. | H8: =ROUND(Parameters!$B$4/E8,0) -> 59 | I8: =INT(Parameters!$B$5/E8) -> 441 | J8: =H8*E8 -> 4012
A9: ARCM | B9: Arcwave Communications | C9: Telecommunications | D9: Mobile and broadband network operator with high debt from its 5G build-out. | E9: 82 | F9: High | G9: Debt-heavy, so sensitive to interest rates. Bidding in the 6G spectrum auction. | H9: =ROUND(Parameters!$B$4/E9,0) -> 49 | I9: =INT(Parameters!$B$5/E9) -> 365 | J9: =H9*E9 -> 4018
A10: GRNF | B10: Greenfield Harvest Foods | C10: Agriculture and food | D10: Grain, dairy and packaged foods. Exports a large share of its output. | E10: 61 | F10: High | G10: Exports via the Port of Ashmouth. Harvest yields drive annual results. | H10: =ROUND(Parameters!$B$4/E10,0) -> 66 | I10: =INT(Parameters!$B$5/E10) -> 491 | J10: =H10*E10 -> 4026
A11: SLRD | B11: Solaris Ridge Renewables | C11: Renewable infrastructure | D11: Builds and operates solar and wind farms financed with long-term borrowing. | E11: 110 | F11: Very high | G11: Depends on government subsidy policy and interest rates. Buys gearboxes from Forgeline. | H11: =ROUND(Parameters!$B$4/E11,0) -> 36 | I11: =INT(Parameters!$B$5/E11) -> 272 | J11: =H11*E11 -> 3960
I12: Total | J12: =SUM(J2:J11) -> 40044
I13: + cash | J13: =Parameters!$B$2-J12 -> 59956
I14: Start equity | J14: =J12+J13 -> 100000

Sheet Hidden State
A1: Ticker | B1: Start | C1: R1 % | D1: R2 % | E1: R3 % | F1: R4 % | G1: R5 % | H1: R6 % | I1: R7 % | J1: R8 % | K1: R9 % | L1: R10 % | M1: F0 | N1: F1 | O1: F2 | P1: F3 | Q1: F4 | R1: F5 | S1: F6 | T1: F7 | U1: F8 | V1: F9 | W1: F10 | X1: Total return
A2: NVTX | B2: =Stocks!E2 -> 142 | C2: 0.03 | D2: -0.07 | E2: 0.02 | F2: -0.03 | G2: -0.08 | H2: 0.03 | I2: -0.03 | J2: 0.05 | K2: 0.04 | L2: 0.02 | M2: =B2 -> 142 | N2: =M2*(1+C2) -> 146.26 | O2: =N2*(1+D2) -> 136.0218 | P2: =O2*(1+E2) -> 138.74224 | Q2: =P2*(1+F2) -> 134.57997 | R2: =Q2*(1+G2) -> 123.81357 | S2: =R2*(1+H2) -> 127.52798 | T2: =S2*(1+I2) -> 123.70214 | U2: =T2*(1+J2) -> 129.88725 | ... W2: =V2*(1+L2) -> 137.78439 | X2: =W2/B2-1 -> -0.029687389
A3: HBFG | B3: =Stocks!E3 -> 88 | C3: 0.01 | D3: 0.02 | E3: 0 | F3: 0 | G3: 0.1 | H3: 0.02 | I3: -0.09 | J3: 0.03 | K3: -0.04 | L3: -0.05 | M3: =B3 -> 88 | N3: =M3*(1+C3) -> 88.88 | O3: =N3*(1+D3) -> 90.6576 | P3: =O3*(1+E3) -> 90.6576 | Q3: =P3*(1+F3) -> 90.6576 | R3: =Q3*(1+G3) -> 99.72336 | S3: =R3*(1+H3) -> 101.71783 | T3: =S3*(1+I3) -> 92.563223 | U3: =T3*(1+J3) -> 95.340119 | ... W3: =V3*(1+L3) -> 86.950189 | X3: =W3/B3-1 -> -0.011929671
A4: PTRL | B4: =Stocks!E4 -> 74 | C4: -0.02 | D4: 0.01 | E4: -0.04 | F4: 0.02 | G4: -0.03 | H4: 0.04 | I4: 0.02 | J4: 0.14 | K4: -0.03 | L4: 0.03 | M4: =B4 -> 74 | N4: =M4*(1+C4) -> 72.52 | O4: =N4*(1+D4) -> 73.2452 | P4: =O4*(1+E4) -> 70.315392 | Q4: =P4*(1+F4) -> 71.7217 | R4: =Q4*(1+G4) -> 69.570049 | S4: =R4*(1+H4) -> 72.352851 | T4: =S4*(1+I4) -> 73.799908 | U4: =T4*(1+J4) -> 84.131895 | ... W4: =V4*(1+L4) -> 84.056176 | X4: =W4/B4-1 -> 0.13589427
A5: CLVH | B5: =Stocks!E5 -> 126 | C5: 0.02 | D5: 0.05 | E5: 0.01 | F5: 0 | G5: 0.02 | H5: 0.06 | I5: 0.01 | J5: -0.12 | K5: -0.02 | L5: 0.03 | M5: =B5 -> 126 | N5: =M5*(1+C5) -> 128.52 | O5: =N5*(1+D5) -> 134.946 | P5: =O5*(1+E5) -> 136.29546 | Q5: =P5*(1+F5) -> 136.29546 | R5: =Q5*(1+G5) -> 139.02137 | S5: =R5*(1+H5) -> 147.36265 | T5: =S5*(1+I5) -> 148.83628 | U5: =T5*(1+J5) -> 130.97592 | ... W5: =V5*(1+L5) -> 132.2071 | X5: =W5/B5-1 -> 0.049262684
A6: MRLW | B6: =Stocks!E6 -> 64 | C6: 0.01 | D6: -0.01 | E6: 0.02 | F6: -0.09 | G6: -0.05 | H6: 0.03 | I6: -0.02 | J6: 0.04 | K6: 0.05 | L6: 0.06 | M6: =B6 -> 64 | N6: =M6*(1+C6) -> 64.64 | O6: =N6*(1+D6) -> 63.9936 | P6: =O6*(1+E6) -> 65.273472 | Q6: =P6*(1+F6) -> 59.39886 | R6: =Q6*(1+G6) -> 56.428917 | S6: =R6*(1+H6) -> 58.121784 | T6: =S6*(1+I6) -> 56.959348 | U6: =T6*(1+J6) -> 59.237722 | ... W6: =V6*(1+L6) -> 65.931585 | X6: =W6/B6-1 -> 0.030181014
A7: FRGE | B7: =Stocks!E7 -> 96 | C7: 0.02 | D7: -0.02 | E7: 0.03 | F7: -0.05 | G7: -0.04 | H7: 0.04 | I7: -0.03 | J7: -0.06 | K7: 0.03 | L7: 0.02 | M7: =B7 -> 96 | N7: =M7*(1+C7) -> 97.92 | O7: =N7*(1+D7) -> 95.9616 | P7: =O7*(1+E7) -> 98.840448 | Q7: =P7*(1+F7) -> 93.898426 | R7: =Q7*(1+G7) -> 90.142489 | S7: =R7*(1+H7) -> 93.748188 | T7: =S7*(1+I7) -> 90.935742 | U7: =T7*(1+J7) -> 85.479598 | ... W7: =V7*(1+L7) -> 89.804866 | X7: =W7/B7-1 -> -0.06453265
A8: TDWL | B8: =Stocks!E8 -> 68 | C8: 0 | D8: 0.01 | E8: 0.01 | F8: 0.09 | G8: -0.02 | H8: -0.06 | I8: -0.02 | J8: 0.02 | K8: 0.02 | L8: -0.03 | M8: =B8 -> 68 | N8: =M8*(1+C8) -> 68 | O8: =N8*(1+D8) -> 68.68 | P8: =O8*(1+E8) -> 69.3668 | Q8: =P8*(1+F8) -> 75.609812 | R8: =Q8*(1+G8) -> 74.097616 | S8: =R8*(1+H8) -> 69.651759 | T8: =S8*(1+I8) -> 68.258724 | U8: =T8*(1+J8) -> 69.623898 | ... W8: =V8*(1+L8) -> 68.885885 | X8: =W8/B8-1 -> 0.013027718
A9: ARCM | B9: =Stocks!E9 -> 82 | C9: -0.01 | D9: 0 | E9: -0.03 | F9: 0.01 | G9: -0.04 | H9: -0.02 | I9: -0.03 | J9: 0.03 | K9: 0.08 | L9: 0.02 | M9: =B9 -> 82 | N9: =M9*(1+C9) -> 81.18 | O9: =N9*(1+D9) -> 81.18 | P9: =O9*(1+E9) -> 78.7446 | Q9: =P9*(1+F9) -> 79.532046 | R9: =Q9*(1+G9) -> 76.350764 | S9: =R9*(1+H9) -> 74.823749 | T9: =S9*(1+I9) -> 72.579036 | U9: =T9*(1+J9) -> 74.756408 | ... W9: =V9*(1+L9) -> 82.351659 | X9: =W9/B9-1 -> 0.0042885184
A10: GRNF | B10: =Stocks!E10 -> 61 | C10: 0.01 | D10: 0.02 | E10: -0.01 | F10: -0.06 | G10: 0.01 | H10: 0.04 | I10: 0.01 | J10: 0 | K10: 0.03 | L10: 0.07 | M10: =B10 -> 61 | N10: =M10*(1+C10) -> 61.61 | O10: =N10*(1+D10) -> 62.8422 | P10: =O10*(1+E10) -> 62.213778 | Q10: =P10*(1+F10) -> 58.480951 | R10: =Q10*(1+G10) -> 59.065761 | S10: =R10*(1+H10) -> 61.428391 | T10: =S10*(1+I10) -> 62.042675 | U10: =T10*(1+J10) -> 62.042675 | ... W10: =V10*(1+L10) -> 68.377232 | X10: =W10/B10-1 -> 0.12093823
A11: SLRD | B11: =Stocks!E11 -> 110 | C11: 0.03 | D11: 0.01 | E11: 0.08 | F11: -0.02 | G11: -0.12 | H11: 0.02 | I11: -0.04 | J11: -0.2 | K11: 0.05 | L11: -0.03 | M11: =B11 -> 110 | N11: =M11*(1+C11) -> 113.3 | O11: =N11*(1+D11) -> 114.433 | P11: =O11*(1+E11) -> 123.58764 | Q11: =P11*(1+F11) -> 121.11589 | R11: =Q11*(1+G11) -> 106.58198 | S11: =R11*(1+H11) -> 108.71362 | T11: =S11*(1+I11) -> 104.36508 | U11: =T11*(1+J11) -> 83.49206 | ... W11: =V11*(1+L11) -> 85.036664 | X11: =W11/B11-1 -> -0.22693942

Sheet Public News
A1: Round | B1: Round title | C1: Headline | D1: Body | E1: Purpose | F1: Hidden state (organiser only)
A2: 1 | B2: Initial Positions | C2: Valdoria GDP grows 1.8%, in line with forecasts | D2: The Statistics Office reports steady third-quarter growth. Consumer confidence is unchanged. Novatex confirms its flagship handset launches next month. | E2: Teach the market and establish opening beliefs. Calm round, no shock. | F2: Economy steady. Small, mostly positive drifts. Petralis licence decision quietly delayed.
A3: 1 | B3: Initial Positions | C3: Energy ministry to rule on new offshore licences 'in due course' | D3: Petralis Energy is among the applicants. No date has been set. | E3: Teach the market and establish opening beliefs. Calm round, no shock. | F3: Economy steady. Small, mostly positive drifts. Petralis licence decision quietly delayed.
A4: 2 | B4: Conflicting Signals | C4: Novatex: revenue up 14%, gross margin falls from 41% to 36% | D4: Management calls the margin decline 'temporary' but gives no timetable. | E4: Test trust in private information versus public evidence. Signals about Novatex conflict. | F4: Novatex margin compression is structural (component costs), outweighing strong unit sales. Calvera interim data genuinely strong.
A5: 2 | B5: Conflicting Signals | C5: Calvera publishes interim VX-7 trial data | D5: The arthritis drug shows a 'statistically significant' improvement. Full data and a regulatory decision are expected later this season. | E5: Test trust in private information versus public evidence. Signals about Novatex conflict. | F5: Novatex margin compression is structural (component costs), outweighing strong unit sales. Calvera interim data genuinely strong.
A6: 3 | B6: Crowd Behaviour | C6: Parliament opens hearings on the Renewable Infrastructure Subsidy Act | D6: A vote is expected later this season. Energy producers warn of higher carbon costs. | E6: Make anonymous order flow strategically relevant. Teams decide whether flow is information or noise. | F6: Subsidy hearings are genuinely positive for renewables and their suppliers. Spectrum auction will be expensive for Arcwave.
A7: 3 | B7: Crowd Behaviour | C7: Telecom regulator opens consultation on the 6G spectrum auction | D7: Reserve prices have not been published. | E7: Make anonymous order flow strategically relevant. Teams decide whether flow is information or noise. | F7: Subsidy hearings are genuinely positive for renewables and their suppliers. Spectrum auction will be expensive for Arcwave.
A8: 4 | B8: Supply-Chain Discovery | C8: Dockworkers' strike shuts the Port of Ashmouth | D8: Valdoria's largest container port is expected to remain closed for about ten days. Ships are queuing offshore. | E8: Test second-order reasoning. One disruption helps one company and hurts others. | F8: Port strike hurts importers and exporters; Tidewell's inland rail corridor earns emergency surcharges and is a net winner.
A9: 5 | B9: Macroeconomic Shift | C9: Central Bank surprises with a 0.75-point rate rise | D9: The Bank signals further increases to fight inflation. The Valdorian crown strengthens sharply against major currencies. | E9: Introduce cross-stock relationships. A rate shock moves sectors in different directions. | F9: Rate hike: banks win; leveraged and growth companies lose; defensives hold up.
A10: 6 | B10: Rumour and Verification | C10: Reports: Calvera's VX-7 approval 'imminent' | D10: Unconfirmed reports say the regulator will approve the arthritis drug this week. | E10: Make research credits valuable. Two rumours: one partly true, one false. | F10: VX-7 approval comes with a restricted label (smaller market than hoped). Arcwave takeover is false. Port strike settles.
A11: 6 | B11: Rumour and Verification | C11: Blog claims Arcwave is a takeover target | D11: A financial blog says a foreign operator is preparing a bid. Arcwave declined to comment. | E11: Make research credits valuable. Two rumours: one partly true, one false. | F11: VX-7 approval comes with a restricted label (smaller market than hoped). Arcwave takeover is false. Port strike settles.
A12: 7 | B12: Liquidity Shock | C12: Hedge fund Corvane Capital collapses | D12: Harbourline Financial confirms 'manageable' exposure. Several lenders are reviewing positions. | E12: Test execution and risk management. Market-maker capacity drops, spreads widen (pre-announced in the rulebook). | F12: Harbourline's hedge-fund exposure is larger than admitted. Broad risk-off move.
A13: 7 | B13: Liquidity Shock | C13: Exchange notice: reduced liquidity this round | D13: As set out in the rulebook, market-maker spreads are wider and depth is thinner in all stocks for Round 7. | E13: Test execution and risk management. Market-maker capacity drops, spreads widen (pre-announced in the rulebook). | F13: Harbourline's hedge-fund exposure is larger than admitted. Broad risk-off move.
... A18: 10 | B18: The Endgame | C18: Results day: all ten companies report full-year numbers | D18: Headline: Valdoria avoids recession as consumer spending recovers. This is the final trading round. | E18: Close cleanly. Same rules and limits; no special final mechanic. | F18: Full-year results: consumer recovery, record harvest, Harbourline suspends dividend, freight normalises.

Sheet Private Signals
A1: Signal | B1: Round | C1: Groups | D1: Ticker | E1: Source (shown) | F1: Stated reliability | G1: Text shown to teams | H1: Implied dir (+1/-1) | I1: Target round | J1: True class | K1: Actual move | L1: Edge (pts) | M1: Truth (debrief)
A2: S1-1 | B2: 1 | C2: A, D | D2: NVTX | E2: Industry contact | F2: Medium | G2: Novatex handset pre-orders are tracking ahead of last year's launch. | H2: 1 | I2: 1 | J2: ACCURATE | K2: =INDEX('Hidden State'!$C$2:$L$11,MATCH(D2,'Hidden State'!$A$2:$A$11,0),I2) -> 0.03 | L2: =H2*K2*100 -> 3 | M2: True. Small positive effect this round.
A3: S1-2 | B3: 1 | C3: B, E | D3: PTRL | E3: Market chatter | F3: Low | G3: Petralis is about to be awarded a large new offshore licence. | H3: 1 | I3: 1 | J3: MISLEADING | K3: =INDEX('Hidden State'!$C$2:$L$11,MATCH(D3,'Hidden State'!$A$2:$A$11,0),I3) -> -0.02 | L3: =H3*K3*100 -> -2 | M3: False. The decision was delayed indefinitely.
A4: S1-3 | B4: 1 | C4: C, F | D4: SLRD | E4: Analyst research | F4: Medium-high | G4: Solaris Ridge's quarterly installations came in slightly above plan. | H4: 1 | I4: 1 | J4: ACCURATE | K4: =INDEX('Hidden State'!$C$2:$L$11,MATCH(D4,'Hidden State'!$A$2:$A$11,0),I4) -> 0.03 | L4: =H4*K4*100 -> 3 | M4: True. Small positive effect.
A5: S2-1 | B5: 2 | C5: D, F | D5: NVTX | E5: Industry contact | F5: Medium | G5: Retail channel checks: stores are reordering Novatex devices; demand is strong. | H5: 1 | I5: 2 | J5: INCOMPLETE | K5: =INDEX('Hidden State'!$C$2:$L$11,MATCH(D5,'Hidden State'!$A$2:$A$11,0),I5) -> -0.07 | L5: =H5*K5*100 -> -7 | M5: Demand really is strong, but margins matter more to value. Stock fell.
A6: S2-2 | B6: 2 | C6: B, C | D6: CLVH | E6: Analyst research | F6: Medium-high | G6: Detailed VX-7 tables show the effect size is larger than the headline suggests. | H6: 1 | I6: 2 | J6: ACCURATE | K6: =INDEX('Hidden State'!$C$2:$L$11,MATCH(D6,'Hidden State'!$A$2:$A$11,0),I6) -> 0.05 | L6: =H6*K6*100 -> 5 | M6: True.
A7: S2-3 | B7: 2 | C7: A, E | D7: NVTX | E7: Analyst research | F7: Medium-high | G7: Novatex's margin decline will continue into next year as component contracts reprice. | H7: -1 | I7: 2 | J7: ACCURATE | K7: =INDEX('Hidden State'!$C$2:$L$11,MATCH(D7,'Hidden State'!$A$2:$A$11,0),I7) -> -0.07 | L7: =H7*K7*100 -> 7 | M7: True. The margin issue is structural.
A8: S3-1 | B8: 3 | C8: D, E | D8: SLRD | E8: Industry contact | F8: Medium | G8: A large institutional fund is quietly accumulating renewable-infrastructure stocks. | H8: 1 | I8: 3 | J8: ACCURATE | K8: =INDEX('Hidden State'!$C$2:$L$11,MATCH(D8,'Hidden State'!$A$2:$A$11,0),I8) -> 0.08 | L8: =H8*K8*100 -> 8 | M8: True, and the fundamentals supported it.
A9: S3-2 | B9: 3 | C9: A, C | D9: ARCM | E9: Market chatter | F9: Low | G9: Arcwave expects to win 6G spectrum cheaply because few rivals will bid. | H9: 1 | I9: 3 | J9: MISLEADING | K9: =INDEX('Hidden State'!$C$2:$L$11,MATCH(D9,'Hidden State'!$A$2:$A$11,0),I9) -> -0.03 | L9: =H9*K9*100 -> -3 | M9: False. Reserve prices will be high.
A10: S3-3 | B10: 3 | C10: B, F | D10: FRGE | E10: Industry contact | F10: Medium | G10: Forgeline has quietly signed a supply deal for wind-turbine gearboxes. | H10: 1 | I10: 3 | J10: ACCURATE | K10: =INDEX('Hidden State'!$C$2:$L$11,MATCH(D10,'Hidden State'!$A$2:$A$11,0),I10) -> 0.03 | L10: =H10*K10*100 -> 3 | M10: True. Second-order beneficiary of the subsidy story.
A11: S4-1 | B11: 4 | C11: A, F | D11: TDWL | E11: Industry contact | F11: Medium | G11: Tidewell's rail-freight corridor is fully booked at emergency rates for the next month. | H11: 1 | I11: 4 | J11: ACCURATE | K11: =INDEX('Hidden State'!$C$2:$L$11,MATCH(D11,'Hidden State'!$A$2:$A$11,0),I11) -> 0.09 | L11: =H11*K11*100 -> 9 | M11: True. Tidewell is a net winner from the strike.
A12: S4-2 | B12: 4 | C12: B, D | D12: MRLW | E12: Market chatter | F12: Low | G12: Marlowe & Kent brought its holiday stock in early this year, before the strike. | H12: 1 | I12: 4 | J12: MISLEADING | K12: =INDEX('Hidden State'!$C$2:$L$11,MATCH(D12,'Hidden State'!$A$2:$A$11,0),I12) -> -0.09 | L12: =H12*K12*100 -> -9 | M12: False. Most holiday stock is stuck on ships at Ashmouth.
A13: S4-3 | B13: 4 | C13: C, E | D13: FRGE | E13: Analyst research | F13: Medium-high | G13: Forgeline's critical imported bearings are sitting in containers at Ashmouth. | H13: -1 | I13: 4 | J13: ACCURATE | K13: =INDEX('Hidden State'!$C$2:$L$11,MATCH(D13,'Hidden State'!$A$2:$A$11,0),I13) -> -0.05 | L13: =H13*K13*100 -> 5 | M13: True. Production delays.
... A31: S10-3 | B31: 10 | C31: E, F | D31: CLVH | E31: Analyst research | F31: Medium-high | G31: Calvera's full-year results include a one-off licensing gain. | H31: 1 | I31: 10 | J31: ACCURATE | K31: =INDEX('Hidden State'!$C$2:$L$11,MATCH(D31,'Hidden State'!$A$2:$A$11,0),I31) -> 0.03 | L31: =H31*K31*100 -> 3 | M31: True. Modest positive effect.

Sheet Allocation
A1: Round | B1: A | C1: B | D1: C | E1: D | F1: E | G1: F
A2: 1 | B2: S1-1 · ACC | C2: S1-2 · MIS | D2: S1-3 · ACC | E2: S1-1 · ACC | F2: S1-2 · MIS | G2: S1-3 · ACC
A3: 2 | B3: S2-3 · ACC | C3: S2-2 · ACC | D3: S2-2 · ACC | E3: S2-1 · INC | F3: S2-3 · ACC | G3: S2-1 · INC
A4: 3 | B4: S3-2 · MIS | C4: S3-3 · ACC | D4: S3-2 · MIS | E4: S3-1 · ACC | F4: S3-1 · ACC | G4: S3-3 · ACC
A5: 4 | B5: S4-1 · ACC | C5: S4-2 · MIS | D5: S4-3 · ACC | E5: S4-2 · MIS | F5: S4-3 · ACC | G5: S4-1 · ACC
A6: 5 | B6: S5-3 · MIS | C6: S5-1 · ACC | D6: S5-2 · OUT | E6: S5-3 · MIS | F6: S5-1 · ACC | G6: S5-2 · OUT
A7: 6 | B7: S6-3 · ACC | C7: S6-3 · ACC | D7: S6-1 · INC | E7: S6-1 · INC | F7: S6-2 · MIS | G7: S6-2 · MIS
A8: 7 | B8: S7-3 · ACC | C8: S7-2 · MIS | D8: S7-1 · ACC | E8: S7-1 · ACC | F8: S7-3 · ACC | G8: S7-2 · MIS
A9: 8 | B9: S8-3 · OUT | C9: S8-3 · OUT | D9: S8-1 · MIS | E9: S8-2 · ACC | F9: S8-1 · MIS | G9: S8-2 · ACC
A10: 9 | B10: S9-2 · ACC | C10: S9-1 · ACC | D10: S9-1 · ACC | E10: S9-3 · MIS | F10: S9-3 · MIS | G10: S9-2 · ACC
A11: 10 | B11: S10-2 · MIS | C11: S10-1 · ACC | D11: S10-2 · MIS | E11: S10-1 · ACC | F11: S10-3 · ACC | G11: S10-3 · ACC
A13: Team → group: team number n goes to group index ((n − 1) mod 6). E.g. teams 1, 7, 13, 19, 25 → A.

Sheet Balance Check
A1: Group | B1: Signals | C1: Accurate | D1: Incomplete | E1: Outdated | F1: Misleading | G1: Total edge (pts)
A2: A | B2: =COUNTIF('Private Signals'!$C$2:$C$31,"*A*") -> 10 | C2: =COUNTIFS('Private Signals'!$C$2:$C$31,"*A*",'Private Signals'!$J$2:$J$31,"ACCURATE") -> 6 | D2: =COUNTIFS('Private Signals'!$C$2:$C$31,"*A*",'Private Signals'!$J$2:$J$31,"INCOMPLETE") -> 0 | E2: =COUNTIFS('Private Signals'!$C$2:$C$31,"*A*",'Private Signals'!$J$2:$J$31,"OUTDATED") -> 1 | F2: =COUNTIFS('Private Signals'!$C$2:$C$31,"*A*",'Private Signals'!$J$2:$J$31,"MISLEADING") -> 3 | G2: =SUMIF('Private Signals'!$C$2:$C$31,"*A*",'Private Signals'!$L$2:$L$31) -> 4
A3: B | B3: =COUNTIF('Private Signals'!$C$2:$C$31,"*B*") -> 10 | C3: =COUNTIFS('Private Signals'!$C$2:$C$31,"*B*",'Private Signals'!$J$2:$J$31,"ACCURATE") -> 6 | D3: =COUNTIFS('Private Signals'!$C$2:$C$31,"*B*",'Private Signals'!$J$2:$J$31,"INCOMPLETE") -> 0 | E3: =COUNTIFS('Private Signals'!$C$2:$C$31,"*B*",'Private Signals'!$J$2:$J$31,"OUTDATED") -> 1 | F3: =COUNTIFS('Private Signals'!$C$2:$C$31,"*B*",'Private Signals'!$J$2:$J$31,"MISLEADING") -> 3 | G3: =SUMIF('Private Signals'!$C$2:$C$31,"*B*",'Private Signals'!$L$2:$L$31) -> 6
A4: C | B4: =COUNTIF('Private Signals'!$C$2:$C$31,"*C*") -> 10 | C4: =COUNTIFS('Private Signals'!$C$2:$C$31,"*C*",'Private Signals'!$J$2:$J$31,"ACCURATE") -> 5 | D4: =COUNTIFS('Private Signals'!$C$2:$C$31,"*C*",'Private Signals'!$J$2:$J$31,"INCOMPLETE") -> 1 | E4: =COUNTIFS('Private Signals'!$C$2:$C$31,"*C*",'Private Signals'!$J$2:$J$31,"OUTDATED") -> 1 | F4: =COUNTIFS('Private Signals'!$C$2:$C$31,"*C*",'Private Signals'!$J$2:$J$31,"MISLEADING") -> 3 | G4: =SUMIF('Private Signals'!$C$2:$C$31,"*C*",'Private Signals'!$L$2:$L$31) -> 6
A5: D | B5: =COUNTIF('Private Signals'!$C$2:$C$31,"*D*") -> 10 | C5: =COUNTIFS('Private Signals'!$C$2:$C$31,"*D*",'Private Signals'!$J$2:$J$31,"ACCURATE") -> 5 | D5: =COUNTIFS('Private Signals'!$C$2:$C$31,"*D*",'Private Signals'!$J$2:$J$31,"INCOMPLETE") -> 2 | E5: =COUNTIFS('Private Signals'!$C$2:$C$31,"*D*",'Private Signals'!$J$2:$J$31,"OUTDATED") -> 0 | F5: =COUNTIFS('Private Signals'!$C$2:$C$31,"*D*",'Private Signals'!$J$2:$J$31,"MISLEADING") -> 3 | G5: =SUMIF('Private Signals'!$C$2:$C$31,"*D*",'Private Signals'!$L$2:$L$31) -> 5
A6: E | B6: =COUNTIF('Private Signals'!$C$2:$C$31,"*E*") -> 10 | C6: =COUNTIFS('Private Signals'!$C$2:$C$31,"*E*",'Private Signals'!$J$2:$J$31,"ACCURATE") -> 6 | D6: =COUNTIFS('Private Signals'!$C$2:$C$31,"*E*",'Private Signals'!$J$2:$J$31,"INCOMPLETE") -> 0 | E6: =COUNTIFS('Private Signals'!$C$2:$C$31,"*E*",'Private Signals'!$J$2:$J$31,"OUTDATED") -> 0 | F6: =COUNTIFS('Private Signals'!$C$2:$C$31,"*E*",'Private Signals'!$J$2:$J$31,"MISLEADING") -> 4 | G6: =SUMIF('Private Signals'!$C$2:$C$31,"*E*",'Private Signals'!$L$2:$L$31) -> 7
A7: F | B7: =COUNTIF('Private Signals'!$C$2:$C$31,"*F*") -> 10 | C7: =COUNTIFS('Private Signals'!$C$2:$C$31,"*F*",'Private Signals'!$J$2:$J$31,"ACCURATE") -> 6 | D7: =COUNTIFS('Private Signals'!$C$2:$C$31,"*F*",'Private Signals'!$J$2:$J$31,"INCOMPLETE") -> 1 | E7: =COUNTIFS('Private Signals'!$C$2:$C$31,"*F*",'Private Signals'!$J$2:$J$31,"OUTDATED") -> 1 | F7: =COUNTIFS('Private Signals'!$C$2:$C$31,"*F*",'Private Signals'!$J$2:$J$31,"MISLEADING") -> 2 | G7: =SUMIF('Private Signals'!$C$2:$C$31,"*F*",'Private Signals'!$L$2:$L$31) -> 8
A9: Edge spread (max − min) | G9: =MAX(G2:G7)-MIN(G2:G7) -> 4
A10: Target: spread ≤ 6 pts and accurate counts within 1 of each other.

Sheet Research
A1: Research ID | B1: Round | C1: Title | D1: Cost (credits) | E1: Result revealed
A2: R1-1 | B2: 1 | C2: Petralis licence: second source | D2: 1 | E2: A ministry official says no licence decisions will be made this quarter.
A3: R2-1 | B3: 2 | C3: Novatex margin breakdown | D3: 1 | E3: Component costs rose 9% and are locked in by annual contracts. No margin recovery is guided for next quarter.
A4: R3-1 | B4: 3 | C4: 6G auction reserve prices | D4: 1 | E4: Draft documents suggest reserve prices roughly double the last auction.
A5: R4-1 | B5: 4 | C5: Who depends on Ashmouth? | D5: 1 | E5: Marlowe & Kent: ~70% of holiday imports. Greenfield: ~40% of exports. Forgeline: key bearings. Tidewell runs the only inland rail alternative.
A6: R5-1 | B6: 5 | C6: Debt and rate-sensitivity table | D6: 1 | E6: Floating-rate debt as share of total: Solaris Ridge 65%, Arcwave 50%, Tidewell 30%, Novatex 10%. Harbourline earns more on floating-rate loans.
A7: R6-1 | B7: 6 | C7: Verify the VX-7 approval rumour | D7: 1 | E7: Second source: approval is expected, but the label will likely be restricted to severe cases (about a third of the target market).
A8: R6-2 | B8: 6 | C8: Verify the Arcwave takeover rumour | D8: 1 | E8: Second source: the banker mandate is for a bond refinancing. No bidder has been identified.
A9: R6-3 | B9: 6 | C9: Port of Ashmouth status | D9: 1 | E9: Union and port authority have a draft agreement; vote scheduled tonight.
A10: R7-1 | B10: 7 | C10: Independent Harbourline exposure estimate | D10: 1 | E10: Exposure is roughly 4% of the bank's equity: painful, not fatal. Dividend at risk.
A11: R8-1 | B11: 8 | C11: Will the subsidy act return? | D11: 1 | E11: Treasury sources: no reintroduction before the next election.
A12: R8-2 | B12: 8 | C12: Ostrava manufacturing check | D12: 1 | E12: Ostrava's plant passed regulatory inspection last month. Supply constraints are resolved.
A13: R9-1 | B13: 9 | C13: Extra macro indicator: core inflation | D13: 1 | E13: Core inflation 2.1%, down from 3.4% two months ago.
A14: R10-1 | B14: 10 | C14: Harbourline dividend check | D14: 1 | E14: Board minutes show the dividend is 'under review' because of Corvane losses.

Sheet Forecasts
A1: Round | B1: Ticker | C1: Question | D1: Correct answer | E1: Points
A2: 3 | B2: SLRD | C2: Will SLRD's reference value finish this round higher or lower than it started? | D2: Up (fundamental) | E2: 1
A3: 6 | B3: CLVH | C3: Will CLVH's reference value finish this round higher or lower than it started? | D3: Up (fundamental) | E3: 1
A4: 9 | B4: ARCM | C4: Will ARCM's reference value finish this round higher or lower than it started? | D4: Up (fundamental) | E4: 1
A6: Scoring is on the published reference value (RV end vs RV start), which includes the small VWAP pull; the fundamental column is the expected answer.
